{
    "os": "Linux-5.14.21-150500.55.97_13.0.78-cray_shasta_c-x86_64-with-glibc2.31",
    "python": "3.9.16",
    "heartbeatAt": "2025-05-15T19:51:59.619958",
    "startedAt": "2025-05-15T19:51:58.929031",
    "docker": null,
    "cuda": null,
    "args": [],
    "state": "running",
    "program": "/pscratch/sd/k/katiekee/PDFParameterInference/cl.py",
    "codePath": "cl.py",
    "git": {
        "remote": "https://github.com/katiekeegan/PDFParameterInference.git",
        "commit": "287e8880963cbd0a52f876f8ccfdb732cb4e5a44"
    },
    "email": "kkeega3@emory.edu",
    "root": "/pscratch/sd/k/katiekee/PDFParameterInference",
    "host": "nid008513",
    "username": "katiekee",
    "executable": "/global/common/software/nersc9/pytorch/2.0.1/bin/python",
    "cpu_count": 64,
    "cpu_count_logical": 128,
    "cpu_freq": {
        "current": 2624.4859140625003,
        "min": 1500.0,
        "max": 2450.0
    },
    "cpu_freq_per_core": [
        {
            "current": 3143.287,
            "min": 1500.0,
            "max": 2450.0
        },
        {
            "current": 2517.103,
            "min": 1500.0,
            "max": 2450.0
        },
        {
            "current": 3143.162,
            "min": 1500.0,
            "max": 2450.0
        },
        {
            "current": 2792.179,
            "min": 1500.0,
            "max": 2450.0
        },
        {
            "current": 2827.202,
            "min": 1500.0,
            "max": 2450.0
        },
        {
            "current": 2769.407,
            "min": 1500.0,
            "max": 2450.0
        },
        {
            "current": 3127.838,
            "min": 1500.0,
            "max": 2450.0
        },
        {
            "current": 3142.061,
            "min": 1500.0,
            "max": 2450.0
        },
        {
            "current": 2889.914,
            "min": 1500.0,
            "max": 2450.0
        },
        {
            "current": 2450.0,
            "min": 1500.0,
            "max": 2450.0
        },
        {
            "current": 2450.0,
            "min": 1500.0,
            "max": 2450.0
        },
        {
            "current": 2679.058,
            "min": 1500.0,
            "max": 2450.0
        },
        {
            "current": 2760.387,
            "min": 1500.0,
            "max": 2450.0
        },
        {
            "current": 3142.88,
            "min": 1500.0,
            "max": 2450.0
        },
        {
            "current": 2766.512,
            "min": 1500.0,
            "max": 2450.0
        },
        {
            "current": 2836.125,
            "min": 1500.0,
            "max": 2450.0
        },
        {
            "current": 2450.0,
            "min": 1500.0,
            "max": 2450.0
        },
        {
            "current": 2682.392,
            "min": 1500.0,
            "max": 2450.0
        },
        {
            "current": 2450.0,
            "min": 1500.0,
            "max": 2450.0
        },
        {
            "current": 2914.126,
            "min": 1500.0,
            "max": 2450.0
        },
        {
            "current": 2895.243,
            "min": 1500.0,
            "max": 2450.0
        },
        {
            "current": 2744.904,
            "min": 1500.0,
            "max": 2450.0
        },
        {
            "current": 2450.0,
            "min": 1500.0,
            "max": 2450.0
        },
        {
            "current": 2450.0,
            "min": 1500.0,
            "max": 2450.0
        },
        {
            "current": 2450.0,
            "min": 1500.0,
            "max": 2450.0
        },
        {
            "current": 2761.944,
            "min": 1500.0,
            "max": 2450.0
        },
        {
            "current": 2513.12,
            "min": 1500.0,
            "max": 2450.0
        },
        {
            "current": 2791.525,
            "min": 1500.0,
            "max": 2450.0
        },
        {
            "current": 2671.266,
            "min": 1500.0,
            "max": 2450.0
        },
        {
            "current": 3026.671,
            "min": 1500.0,
            "max": 2450.0
        },
        {
            "current": 3014.452,
            "min": 1500.0,
            "max": 2450.0
        },
        {
            "current": 2662.037,
            "min": 1500.0,
            "max": 2450.0
        },
        {
            "current": 2978.315,
            "min": 1500.0,
            "max": 2450.0
        },
        {
            "current": 2450.0,
            "min": 1500.0,
            "max": 2450.0
        },
        {
            "current": 2887.262,
            "min": 1500.0,
            "max": 2450.0
        },
        {
            "current": 2926.903,
            "min": 1500.0,
            "max": 2450.0
        },
        {
            "current": 3143.078,
            "min": 1500.0,
            "max": 2450.0
        },
        {
            "current": 2977.957,
            "min": 1500.0,
            "max": 2450.0
        },
        {
            "current": 2950.828,
            "min": 1500.0,
            "max": 2450.0
        },
        {
            "current": 2450.0,
            "min": 1500.0,
            "max": 2450.0
        },
        {
            "current": 3027.097,
            "min": 1500.0,
            "max": 2450.0
        },
        {
            "current": 2450.0,
            "min": 1500.0,
            "max": 2450.0
        },
        {
            "current": 2450.0,
            "min": 1500.0,
            "max": 2450.0
        },
        {
            "current": 2676.949,
            "min": 1500.0,
            "max": 2450.0
        },
        {
            "current": 2902.626,
            "min": 1500.0,
            "max": 2450.0
        },
        {
            "current": 3141.577,
            "min": 1500.0,
            "max": 2450.0
        },
        {
            "current": 2938.885,
            "min": 1500.0,
            "max": 2450.0
        },
        {
            "current": 2450.0,
            "min": 1500.0,
            "max": 2450.0
        },
        {
            "current": 2615.585,
            "min": 1500.0,
            "max": 2450.0
        },
        {
            "current": 2821.085,
            "min": 1500.0,
            "max": 2450.0
        },
        {
            "current": 2651.086,
            "min": 1500.0,
            "max": 2450.0
        },
        {
            "current": 3075.666,
            "min": 1500.0,
            "max": 2450.0
        },
        {
            "current": 3031.09,
            "min": 1500.0,
            "max": 2450.0
        },
        {
            "current": 2726.377,
            "min": 1500.0,
            "max": 2450.0
        },
        {
            "current": 2451.487,
            "min": 1500.0,
            "max": 2450.0
        },
        {
            "current": 2896.839,
            "min": 1500.0,
            "max": 2450.0
        },
        {
            "current": 2555.825,
            "min": 1500.0,
            "max": 2450.0
        },
        {
            "current": 2524.106,
            "min": 1500.0,
            "max": 2450.0
        },
        {
            "current": 2585.946,
            "min": 1500.0,
            "max": 2450.0
        },
        {
            "current": 2450.0,
            "min": 1500.0,
            "max": 2450.0
        },
        {
            "current": 2450.0,
            "min": 1500.0,
            "max": 2450.0
        },
        {
            "current": 2450.0,
            "min": 1500.0,
            "max": 2450.0
        },
        {
            "current": 2583.329,
            "min": 1500.0,
            "max": 2450.0
        },
        {
            "current": 2644.077,
            "min": 1500.0,
            "max": 2450.0
        },
        {
            "current": 3142.634,
            "min": 1500.0,
            "max": 2450.0
        },
        {
            "current": 2756.583,
            "min": 1500.0,
            "max": 2450.0
        },
        {
            "current": 3139.762,
            "min": 1500.0,
            "max": 2450.0
        },
        {
            "current": 3008.513,
            "min": 1500.0,
            "max": 2450.0
        },
        {
            "current": 2735.37,
            "min": 1500.0,
            "max": 2450.0
        },
        {
            "current": 2677.658,
            "min": 1500.0,
            "max": 2450.0
        },
        {
            "current": 3140.411,
            "min": 1500.0,
            "max": 2450.0
        },
        {
            "current": 2883.637,
            "min": 1500.0,
            "max": 2450.0
        },
        {
            "current": 3027.145,
            "min": 1500.0,
            "max": 2450.0
        },
        {
            "current": 2652.987,
            "min": 1500.0,
            "max": 2450.0
        },
        {
            "current": 2652.197,
            "min": 1500.0,
            "max": 2450.0
        },
        {
            "current": 2777.533,
            "min": 1500.0,
            "max": 2450.0
        },
        {
            "current": 2450.0,
            "min": 1500.0,
            "max": 2450.0
        },
        {
            "current": 3127.688,
            "min": 1500.0,
            "max": 2450.0
        },
        {
            "current": 2853.52,
            "min": 1500.0,
            "max": 2450.0
        },
        {
            "current": 2450.0,
            "min": 1500.0,
            "max": 2450.0
        },
        {
            "current": 2828.36,
            "min": 1500.0,
            "max": 2450.0
        },
        {
            "current": 2450.0,
            "min": 1500.0,
            "max": 2450.0
        },
        {
            "current": 2450.0,
            "min": 1500.0,
            "max": 2450.0
        },
        {
            "current": 2450.0,
            "min": 1500.0,
            "max": 2450.0
        },
        {
            "current": 2917.502,
            "min": 1500.0,
            "max": 2450.0
        },
        {
            "current": 2450.0,
            "min": 1500.0,
            "max": 2450.0
        },
        {
            "current": 2782.986,
            "min": 1500.0,
            "max": 2450.0
        },
        {
            "current": 2633.184,
            "min": 1500.0,
            "max": 2450.0
        },
        {
            "current": 2450.0,
            "min": 1500.0,
            "max": 2450.0
        },
        {
            "current": 2713.253,
            "min": 1500.0,
            "max": 2450.0
        },
        {
            "current": 2528.332,
            "min": 1500.0,
            "max": 2450.0
        },
        {
            "current": 2722.306,
            "min": 1500.0,
            "max": 2450.0
        },
        {
            "current": 2450.0,
            "min": 1500.0,
            "max": 2450.0
        },
        {
            "current": 2450.0,
            "min": 1500.0,
            "max": 2450.0
        },
        {
            "current": 2450.0,
            "min": 1500.0,
            "max": 2450.0
        },
        {
            "current": 2450.0,
            "min": 1500.0,
            "max": 2450.0
        },
        {
            "current": 2450.0,
            "min": 1500.0,
            "max": 2450.0
        },
        {
            "current": 2893.453,
            "min": 1500.0,
            "max": 2450.0
        },
        {
            "current": 2832.817,
            "min": 1500.0,
            "max": 2450.0
        },
        {
            "current": 2450.0,
            "min": 1500.0,
            "max": 2450.0
        },
        {
            "current": 3024.63,
            "min": 1500.0,
            "max": 2450.0
        },
        {
            "current": 3137.574,
            "min": 1500.0,
            "max": 2450.0
        },
        {
            "current": 3140.506,
            "min": 1500.0,
            "max": 2450.0
        },
        {
            "current": 2450.0,
            "min": 1500.0,
            "max": 2450.0
        },
        {
            "current": 2450.0,
            "min": 1500.0,
            "max": 2450.0
        },
        {
            "current": 2450.0,
            "min": 1500.0,
            "max": 2450.0
        },
        {
            "current": 2853.617,
            "min": 1500.0,
            "max": 2450.0
        },
        {
            "current": 2450.0,
            "min": 1500.0,
            "max": 2450.0
        },
        {
            "current": 2983.959,
            "min": 1500.0,
            "max": 2450.0
        },
        {
            "current": 3141.976,
            "min": 1500.0,
            "max": 2450.0
        },
        {
            "current": 3138.376,
            "min": 1500.0,
            "max": 2450.0
        },
        {
            "current": 2675.138,
            "min": 1500.0,
            "max": 2450.0
        },
        {
            "current": 3149.683,
            "min": 1500.0,
            "max": 2450.0
        },
        {
            "current": 2450.0,
            "min": 1500.0,
            "max": 2450.0
        },
        {
            "current": 2822.954,
            "min": 1500.0,
            "max": 2450.0
        },
        {
            "current": 3046.209,
            "min": 1500.0,
            "max": 2450.0
        },
        {
            "current": 2717.181,
            "min": 1500.0,
            "max": 2450.0
        },
        {
            "current": 2771.075,
            "min": 1500.0,
            "max": 2450.0
        },
        {
            "current": 3051.918,
            "min": 1500.0,
            "max": 2450.0
        },
        {
            "current": 3139.485,
            "min": 1500.0,
            "max": 2450.0
        },
        {
            "current": 2574.947,
            "min": 1500.0,
            "max": 2450.0
        },
        {
            "current": 2582.9,
            "min": 1500.0,
            "max": 2450.0
        },
        {
            "current": 2509.584,
            "min": 1500.0,
            "max": 2450.0
        },
        {
            "current": 2173.7,
            "min": 1500.0,
            "max": 2450.0
        },
        {
            "current": 2113.703,
            "min": 1500.0,
            "max": 2450.0
        },
        {
            "current": 2450.0,
            "min": 1500.0,
            "max": 2450.0
        },
        {
            "current": 2590.285,
            "min": 1500.0,
            "max": 2450.0
        },
        {
            "current": 2606.769,
            "min": 1500.0,
            "max": 2450.0
        }
    ],
    "disk": {
        "total": 125.59867858886719,
        "used": 0.5734291076660156
    },
    "gpu": "NVIDIA A100-SXM4-80GB",
    "gpu_count": 1,
    "gpu_devices": [
        {
            "name": "NVIDIA A100-SXM4-80GB",
            "memory_total": 85899345920
        }
    ],
    "memory": {
        "total": 251.19735717773438
    }
}
